martin_config/__init__.py
martin_config/__main__.py
martin_config/azfile.py
martin_config/config.py
martin_config/db.py
martin_config/utils.py
martin_config/sql/column_is_accessible.sql
martin_config/sql/delete_col_comment.sql
martin_config/sql/delete_table_comment.sql
martin_config/sql/drop_table.sql
martin_config/sql/func_sources.sql
martin_config/sql/function_is_accessible.sql
martin_config/sql/get_col_comment.sql
martin_config/sql/get_computed_bbox.sql
martin_config/sql/get_estimated_bbox.sql
martin_config/sql/get_table_columns.sql
martin_config/sql/get_table_comment.sql
martin_config/sql/get_table_primary_key.sql
martin_config/sql/list_databases.sql
martin_config/sql/list_schema_tables.sql
martin_config/sql/list_schemas.sql
martin_config/sql/list_tables.sql
martin_config/sql/schema_is_accessible.sql
martin_config/sql/set_col_comment.sql
martin_config/sql/set_table_comment.sql
martin_config/sql/table_exists.sql
martin_config/sql/table_is_accessible.sql
martin_config/test/__init__.py
martin_config-0.1.3.dist-info/METADATA
martin_config-0.1.3.dist-info/WHEEL
martin_config-0.1.3.dist-info/entry_points.txt
martin_config-0.1.3.dist-info/top_level.txt
martin_config-0.1.3.dist-info/RECORD
