Metadata-Version: 2.1
Name: martin-config
Version: 0.1.3
Summary: Generate configuration files for martin vector tile server
Author-email: Ioan Ferencik <ioan.ferencik@undp.org>, Jin Igarashi <jin.igarashi@undp.org>
Classifier: Programming Language :: Python :: 3
Classifier: License :: OSI Approved :: MIT License
Classifier: Operating System :: OS Independent
Requires-Python: >=3.6
Requires-Dist: asyncpg
Requires-Dist: pyyaml
Requires-Dist: python-dotenv
Provides-Extra: azure
Requires-Dist: azure-storage-file-share ; extra == 'azure'
